tetgenExt/_tetgenExt.cpython-37m-x86_64-linux-gnu.so
tetgenExt/_version.py
tetgenExt/pytetgenExt.py
tetgenExt/__init__.py
tetgenExt-0.6.dev0.dist-info/LICENSE
tetgenExt-0.6.dev0.dist-info/top_level.txt
tetgenExt-0.6.dev0.dist-info/METADATA
tetgenExt-0.6.dev0.dist-info/RECORD
tetgenExt-0.6.dev0.dist-info/WHEEL
