Metadata-Version: 2.1
Name: tetgenExt
Version: 0.6.dev0
Summary: Python interface to tetgenExt
Home-page: https://github.com/pyvista/tetgenExt
Author: Alex Kaszynski
Author-email: akascap@gmail.com
Keywords: TetGenExt
Classifier: Intended Audience :: Science/Research
Classifier: License :: OSI Approved :: GNU Affero General Public License v3
Classifier: Development Status :: 4 - Beta
Classifier: Programming Language :: Python :: 3.6
Classifier: Programming Language :: Python :: 3.7
Classifier: Programming Language :: Python :: 3.8
Classifier: Programming Language :: Python :: 3.9
License-File: LICENSE
Requires-Dist: numpy (==1.16.0)
